{
  "generated": "2026-07-17T18:46:54Z",
  "environment": "demo",
  "configured": true,
  "live_orders_enabled": true,
  "mode": "live",
  "account_currency": "GBP",
  "ok": true,
  "detail": "demo account reachable: 4 position(s), free \u00a3286.47",
  "cash": {
    "free": 286.47,
    "total": 490.85,
    "ppl": -3.82,
    "result": -4.45,
    "invested": 208.2,
    "pieCash": 0,
    "blocked": 0
  },
  "positions": [
    {
      "ticker": "WRAP",
      "t212_ticker": "WRTC_US_EQ",
      "shares": 41.13,
      "avg_price": 2.07999027,
      "current_price": 2.08,
      "pnl": -0.18
    },
    {
      "ticker": "SLND",
      "t212_ticker": "LGTO_US_EQ",
      "shares": 60.4652627,
      "avg_price": 1.11005885,
      "current_price": 1.0899,
      "pnl": -0.94
    },
    {
      "ticker": "CAI",
      "t212_ticker": "CAI1_US_EQ",
      "shares": 4.94,
      "avg_price": 17.1902834,
      "current_price": 16.51,
      "pnl": -2.7
    },
    {
      "ticker": "YEXT",
      "t212_ticker": "YEXT_US_EQ",
      "shares": 7.8,
      "avg_price": 5.36025641,
      "current_price": 5.38,
      "pnl": 0
    }
  ],
  "reconciliation": [
    {
      "ticker": "CAI",
      "ledger_shares": 4.9363,
      "broker_shares": 4.94,
      "status": "match"
    },
    {
      "ticker": "SLND",
      "ledger_shares": 60.4652627,
      "broker_shares": 60.4652627,
      "status": "match"
    },
    {
      "ticker": "WRAP",
      "ledger_shares": 41.1342,
      "broker_shares": 41.13,
      "status": "match"
    },
    {
      "ticker": "YEXT",
      "ledger_shares": 7.8044,
      "broker_shares": 7.8,
      "status": "match"
    }
  ]
}